{"viewData":{"url_key":"lg_24lj4540_wu_lj4540wu_series_24_hdtv","name":"LG LJ4540 24\" Class HD LED TV (White)","sku":"1323392","price":"136.99","categories":{"0":{"categoryName":"Televisions","urlKey":"televisions"},"1":{"categoryName":"LG","urlKey":"lg"}},"short_description":"Buy LG LJ4540 24&quot; Class HD LED TV (White) featuring HD 1366 x 768 LED Panel, HDMI Input Triple XD Engine. Review LG LJ4540","long_description":"Enjoy high-definition content with the white LG LJ4540 24\" Class HD LED TV. This 23.6\" LED-backlit LCD panel features a native resolution of 1366 x 768, allowing you to view detailed 720p HD images. Its HDMI input will allow you to connect your digital HD sources, such as HD cable/satellite boxes or game consoles. A remote control is included as an added convenience.","images":{"0":"9cf3593cb15f3a3afade5206ddf99eea-0.jpg","1":"9cf3593cb15f3a3afade5206ddf99eea-1.jpg","2":"9cf3593cb15f3a3afade5206ddf99eea-2.jpg","3":"9cf3593cb15f3a3afade5206ddf99eea-3.jpg","4":"9cf3593cb15f3a3afade5206ddf99eea-4.jpg","5":"9cf3593cb15f3a3afade5206ddf99eea-5.jpg","6":"9cf3593cb15f3a3afade5206ddf99eea-6.jpg"}},"configuration":{},"availability":{"1323392":{"aditional_price":0,"availabile":369}}}
