{"viewData":{"url_key":"sony_xbr49x900f_x900f_series_49_class_hdr_uhd","name":"Sony X900F Series 49\" Class HDR UHD Smart LED TV","sku":"1391672","price":"998.00","categories":{"0":{"categoryName":"Televisions","urlKey":"televisions"},"1":{"categoryName":"Sony","urlKey":"sony"}},"short_description":"Buy Sony X900F Series 49&quot; Class HDR UHD Smart LED TV featuring UHD 3840 x 2160 LED Panel, HDR10-, HLG-, Dolby Vision-Compatible 120 Hz Refresh Rate + Motionflow XR. Review Sony X900F","long_description":"View content at four times the resolution of 1080p with the Sony X900F Series 49\"-Class HDR UHD Smart LED TV. It has a 48.5\" LED display, and incorporates Sony's Motionflow XR technology to digitally enhance fast-moving images to reduce blur. HDR10, Dolby Vision, and HLG compatibility provide a wide color gamut for compatible content. The X900F series has built-in Wi-Fi connectivity to allow access to the Google Play store, your favorite apps, and Internet-based content via its Android operating system, plus content sharing and screen mirroring with your other compatible smart devices such as your smartphone or tablet. The Vewd web browser is also available for download through the Google Play store. With four HDMI inputs, there are multiple options for connecting high-definition video sources. A composite video input is also available for connecting legacy equipment, while three USB ports are onboard for connecting compatible multimedia peripherals like flash drives.","images":{"0":"5324387dfdfe8a47d06c3ea741dca36f-0.jpg","1":"5324387dfdfe8a47d06c3ea741dca36f-1.jpg","2":"5324387dfdfe8a47d06c3ea741dca36f-2.jpg","3":"5324387dfdfe8a47d06c3ea741dca36f-3.jpg","4":"5324387dfdfe8a47d06c3ea741dca36f-4.jpg","5":"5324387dfdfe8a47d06c3ea741dca36f-5.jpg","6":"5324387dfdfe8a47d06c3ea741dca36f-6.jpg","7":"5324387dfdfe8a47d06c3ea741dca36f-7.jpg"}},"configuration":{},"availability":{"1391672":{"aditional_price":0,"availabile":883}}}
